require2fa/README.md
require2fa/__init__.py
require2fa/admin.py
require2fa/apps.py
require2fa/middleware.py
require2fa/models.py
require2fa/views.py
require2fa/migrations/0001_initial.py
require2fa/migrations/__init__.py
require2fa/tests/__init__.py
require2fa/tests/settings.py
require2fa/tests/test_middleware.py
require2fa/tests/urls.py
django_allauth_require2fa-1.2.2.dist-info/METADATA
django_allauth_require2fa-1.2.2.dist-info/WHEEL
django_allauth_require2fa-1.2.2.dist-info/licenses/LICENSE
django_allauth_require2fa-1.2.2.dist-info/RECORD
