Metadata-Version: 2.4
Name: django-allauth-require2fa
Version: 1.2.2
Summary: Site-wide Two-Factor Authentication enforcement middleware for Django applications using django-allauth
Project-URL: Homepage, https://github.com/heysamtexas/django-allauth-require2fa
Project-URL: Documentation, https://github.com/heysamtexas/django-allauth-require2fa#readme
Project-URL: Repository, https://github.com/heysamtexas/django-allauth-require2fa.git
Project-URL: Issues, https://github.com/heysamtexas/django-allauth-require2fa/issues
Project-URL: Changelog, https://github.com/heysamtexas/django-allauth-require2fa/blob/main/CHANGELOG.md
Author: Django Require2FA Contributors
License-Expression: MIT
License-File: LICENSE
Keywords: 2fa,allauth,authentication,django,middleware,security,two-factor
Classifier: Development Status :: 4 - Beta
Classifier: Environment :: Web Environment
Classifier: Framework :: Django
Classifier: Framework :: Django :: 4.2
Classifier: Framework :: Django :: 5.0
Classifier: Framework :: Django :: 5.1
Classifier: Intended Audience :: Developers
Classifier: License :: OSI Approved :: MIT License
Classifier: Operating System :: OS Independent
Classifier: Programming Language :: Python
Classifier: Programming Language :: Python :: 3
Classifier: Programming Language :: Python :: 3.12
Classifier: Programming Language :: Python :: 3.13
Classifier: Topic :: Internet :: WWW/HTTP
Classifier: Topic :: Security
Classifier: Topic :: Software Development :: Libraries :: Python Modules
Requires-Python: >=3.12
Requires-Dist: django-allauth>=0.57.0
Requires-Dist: django-solo>=2.0.0
Requires-Dist: django>=4.2
Requires-Dist: fido2>=2.0.0
Provides-Extra: dev
Requires-Dist: bandit>=1.7.0; extra == 'dev'
Requires-Dist: django-stubs>=4.2.0; extra == 'dev'
Requires-Dist: mypy>=1.5.0; extra == 'dev'
Requires-Dist: pre-commit>=3.0.0; extra == 'dev'
Requires-Dist: ruff>=0.4.0; extra == 'dev'
